prem_utils/__init__.py
prem_utils/errors.py
prem_utils/models.json
prem_utils/types.py
prem_utils/utils.py
prem_utils/connectors/__init__.py
prem_utils/connectors/anthropic.py
prem_utils/connectors/anyscale.py
prem_utils/connectors/azure.py
prem_utils/connectors/base.py
prem_utils/connectors/cloudflare.py
prem_utils/connectors/cohere.py
prem_utils/connectors/deepinfra.py
prem_utils/connectors/fireworksai.py
prem_utils/connectors/groq.py
prem_utils/connectors/lamini.py
prem_utils/connectors/mistral.py
prem_utils/connectors/octoai.py
prem_utils/connectors/openai.py
prem_utils/connectors/openrouter.py
prem_utils/connectors/perplexity.py
prem_utils/connectors/prem.py
prem_utils/connectors/replicate.py
prem_utils/connectors/together.py
prem_utils/connectors/utils.py
prem_utils-0.0.47.dist-info/LICENSE
prem_utils-0.0.47.dist-info/METADATA
prem_utils-0.0.47.dist-info/WHEEL
prem_utils-0.0.47.dist-info/top_level.txt
prem_utils-0.0.47.dist-info/RECORD
