Metadata-Version: 2.1
Name: prem-utils
Version: 0.0.47
Summary: Prem generic utils to use across Prem Components.
Author-email: Filippo Pedrazzini <filippo@premai.io>
License: Apache-2.0
Project-URL: Homepage, https://github.com/premAI-io/prem-utils
Project-URL: Releases, https://github.com/premAI-io/prem-utils/tags
Classifier: Development Status :: 1 - Planning
Classifier: Programming Language :: Python :: 3 :: Only
Requires-Python: >=3.7
License-File: LICENSE
Requires-Dist: openai ==1.13.3
Requires-Dist: tiktoken ==0.6.0
Requires-Dist: cohere ==4.53
Requires-Dist: anthropic ==0.28.0
Requires-Dist: mistralai ==0.1.3
Requires-Dist: python-dotenv ==1.0.0
Requires-Dist: pre-commit ==3.6.0
Requires-Dist: groq ==0.4.1
Requires-Dist: asyncio ==3.4.3
